b_cfn_elasticsearch_cloner/__init__.py
b_cfn_elasticsearch_cloner/resource.py
b_cfn_elasticsearch_cloner/cloner_source/__init__.py
b_cfn_elasticsearch_cloner/cloner_source/dynamodb_decode.py
b_cfn_elasticsearch_cloner/cloner_source/index.py
b_cfn_elasticsearch_cloner/initial_cloner_source/__init__.py
b_cfn_elasticsearch_cloner/initial_cloner_source/action.py
b_cfn_elasticsearch_cloner/initial_cloner_source/cfnresponse.py
b_cfn_elasticsearch_cloner/initial_cloner_source/index.py
b_cfn_elasticsearch_cloner-0.2.1.dist-info/LICENSE
b_cfn_elasticsearch_cloner-0.2.1.dist-info/METADATA
b_cfn_elasticsearch_cloner-0.2.1.dist-info/WHEEL
b_cfn_elasticsearch_cloner-0.2.1.dist-info/top_level.txt
b_cfn_elasticsearch_cloner-0.2.1.dist-info/RECORD
